pytest_report_plugin/__init__.py
pytest_report_plugin/log_helper.py
pytest_report_plugin/py.typed
pytest_report_plugin/telegram.py
pytest_report_plugin/zephyr.py
pytest_report_plugin/zephyr_client.py
pytest_zephyr_telegram-0.4.0.dist-info/METADATA
pytest_zephyr_telegram-0.4.0.dist-info/WHEEL
pytest_zephyr_telegram-0.4.0.dist-info/entry_points.txt
pytest_zephyr_telegram-0.4.0.dist-info/top_level.txt
pytest_zephyr_telegram-0.4.0.dist-info/RECORD
